imu/Cargo.toml
imu/__init__.py
imu/bindings.cpython-313-x86_64-linux-gnu.so
imu/py.typed
imu/requirements-dev.txt
imu/requirements.txt
imu/bindings/Cargo.toml
imu/bindings/src/hexmove.rs
imu/bindings/src/hiwonder.rs
imu/bindings/src/lib.rs
imu/bmi088/Cargo.toml
imu/bmi088/src/lib.rs
imu/bmi088/src/registers.rs
imu/bmi088/src/bin/read_bmi088.rs
imu/bno055/Cargo.toml
imu/bno055/src/lib.rs
imu/bno055/src/registers.rs
imu/bno055/src/bin/read_bno055.rs
imu/hexmove/Cargo.toml
imu/hexmove/src/lib.rs
imu/hexmove/src/bin/read_hexmove.rs
imu/hiwonder/Cargo.toml
imu/hiwonder/src/lib.rs
imu/hiwonder/src/bin/read_hiwonder.rs
imu/src/lib.rs
kscale_imu.libs/libattr-4f2a9577.so.1.1.0
kscale_imu.libs/libbz2-a273e504.so.1.0.6
kscale_imu.libs/libcap-79733b59.so.2.22
kscale_imu.libs/libdw-0-780627ce.176.so
kscale_imu.libs/libelf-0-3d9de92a.176.so
kscale_imu.libs/liblzma-004595ca.so.5.2.2
kscale_imu.libs/libudev-1f672570.so.1.6.2
kscale_imu-0.5.0.dist-info/METADATA
kscale_imu-0.5.0.dist-info/WHEEL
kscale_imu-0.5.0.dist-info/top_level.txt
kscale_imu-0.5.0.dist-info/RECORD
kscale_imu-0.5.0.dist-info/licenses/LICENSE
